{"lastUsed":1733773460917,"path":"C:\/Users\/vslen\/Projects\/blogpessoal","projectCount":1,"recentFiles":[{"path":"\/blogpessoal\/src\/main\/java\/com\/generation\/blogpessoal\/controller","parentWorkspace":"C:\/Users\/vslen\/Projects\/blogpessoal","name":"PostagemController.java","lastModified":1733773460917,"locationURI":"file:\/C:\/Users\/vslen\/Projects\/blogpessoal\/blogpessoal\/blogpessoal\/src\/main\/java\/com\/generation\/blogpessoal\/controller\/PostagemController.java"},{"path":"\/blogpessoal\/src\/main\/java\/com\/generation\/blogpessoal\/repository","parentWorkspace":"C:\/Users\/vslen\/Projects\/blogpessoal","name":"PostagemRepository.java","lastModified":1733741652109,"locationURI":"file:\/C:\/Users\/vslen\/Projects\/blogpessoal\/blogpessoal\/blogpessoal\/src\/main\/java\/com\/generation\/blogpessoal\/repository\/PostagemRepository.java"}]}